[
  {
    "appid": 2482940,
    "name": "小小梦魇VR: 异境回响",
    "header_image": "https://shared.akamai.steamstatic.com/store_item_assets/steam/apps/2482940/a137fc50e2c74545c077c8532688d45f52334917/header_schinese.jpg?t=1776981649",
    "short_description": "《小小梦魇VR：异境回响》是一款黑暗风格的冒险解谜游戏，玩家在其中扮演“黑暗小六”，一名小女孩姿态的神秘人物。在诡谲的世界中前行，解开错综复杂的谜题，并在渴望再次完整的拚死搜索中，逃离恐怖的巨型敌人。",
    "is_free": false,
    "price": "¥ 118.00",
    "original_price": "",
    "discount_percent": 0,
    "genres": [
      "动作",
      "冒险"
    ],
    "release_date": "2026 年 4 月 23 日",
    "review_score": "",
    "store_url": "https://store.steampowered.com/app/2482940"
  },
  {
    "appid": 1206410,
    "name": "月影杀",
    "header_image": "https://shared.akamai.steamstatic.com/store_item_assets/steam/apps/1206410/7a5f71c05819e0102bb53f6429e018af6ba452b5/header_schinese.jpg?t=1776972006",
    "short_description": "《月影杀》是一款黑暗奇幻ARPG, 融合了极具挑战性的战斗, 流畅的跑酷和深度探索. 掌握六大神圣晶魄的远古魔法, 在这场扣人心弦的剧情冒险中揭开神秘诅咒的根源.",
    "is_free": false,
    "price": "¥ 137.00",
    "original_price": "",
    "discount_percent": 0,
    "genres": [
      "动作",
      "冒险",
      "独立",
      "角色扮演"
    ],
    "release_date": "2026 年 4 月 23 日",
    "review_score": "",
    "store_url": "https://store.steampowered.com/app/1206410"
  },
  {
    "appid": 1647310,
    "name": "阵地之王：卫国战争",
    "header_image": "https://shared.akamai.steamstatic.com/store_item_assets/steam/apps/1647310/3a372a7f1fa22c5dea225202142b024b9b4195ef/header_alt_assets_1_schinese.jpg?t=1776963674",
    "short_description": "《阵地之王：卫国战争》是一款二战背景的俯视角战术射击游戏，敌人已经兵临城下，你必须要站出来，士兵！集结你的队伍，向敌人进攻！",
    "is_free": false,
    "price": "¥ 28.80",
    "original_price": "¥ 48.00",
    "discount_percent": 40,
    "genres": [
      "动作",
      "独立",
      "策略"
    ],
    "release_date": "2026 年 4 月 23 日",
    "review_score": "",
    "store_url": "https://store.steampowered.com/app/1647310"
  },
  {
    "appid": 2423760,
    "name": "覆雪之上",
    "header_image": "https://shared.akamai.steamstatic.com/store_item_assets/steam/apps/2423760/db0b0c6428748de265b1c8a796f1108e85e5a1dd/header_schinese.jpg?t=1776978877",
    "short_description": "加入庇护所小队，打造阿尔卑斯山最棒的度假酒店！体验丰富的角色故事，定制专属庇护所，吸引并救援登山客，投身酒店经营，规划登山路线！拿起地图，拉紧夹克，灌满保温壶，迎接60年代最严酷的寒冬吧！",
    "is_free": false,
    "price": "¥ 57.60",
    "original_price": "¥ 64.00",
    "discount_percent": 10,
    "genres": [
      "休闲",
      "独立",
      "模拟",
      "策略"
    ],
    "release_date": "2026 年 4 月 23 日",
    "review_score": "",
    "store_url": "https://store.steampowered.com/app/2423760"
  },
  {
    "appid": 2840470,
    "name": "SimplePlanes 2",
    "header_image": "https://shared.akamai.steamstatic.com/store_item_assets/steam/apps/2840470/910f2b140ddd11546bdc5af6ba9f9b3da165f773/header.jpg?t=1776962034",
    "short_description": "SimplePlanes 回归了！利用强大的程序化部件建造飞机、汽车或任何其他东西！在多人游戏中与好友探索精细的环境，制造混乱，或免费下载 1,000,000 种社区作品。",
    "is_free": false,
    "price": "¥ 68.40",
    "original_price": "¥ 76.00",
    "discount_percent": 10,
    "genres": [
      "独立",
      "竞速",
      "模拟",
      "抢先体验"
    ],
    "release_date": "2026 年 4 月 23 日",
    "review_score": "",
    "store_url": "https://store.steampowered.com/app/2840470"
  },
  {
    "appid": 2364580,
    "name": "Titanium Court",
    "header_image": "https://shared.akamai.steamstatic.com/store_item_assets/steam/apps/2364580/efee60b64009678a60174f470b33f9e741d2eff9/header.jpg?t=1776964206",
    "short_description": "A surreal strategy game for clowns and criminals.",
    "is_free": false,
    "price": "¥ 43.19",
    "original_price": "¥ 53.99",
    "discount_percent": 20,
    "genres": [
      "策略"
    ],
    "release_date": "2026 年 4 月 23 日",
    "review_score": "",
    "store_url": "https://store.steampowered.com/app/2364580"
  },
  {
    "appid": 2759280,
    "name": "Kumitantei: Old-School Slaughter",
    "header_image": "https://shared.akamai.steamstatic.com/store_item_assets/steam/apps/2759280/468d5bc532a998a62eb1056c4a96a98ce34bafc1/header.jpg?t=1776959778",
    "short_description": "以科学之名……互相残杀！1989届学生在一所精英学校被迫卷入一场杀戮游戏。《库米探™：老派杀戮》是一款受复古动漫启发的章节式谋杀谜案冒险卡牌对战游戏。玩家将调查真相、破解谜题、揭露同学的真面目。",
    "is_free": false,
    "price": "¥ 61.20",
    "original_price": "¥ 68.00",
    "discount_percent": 10,
    "genres": [
      "冒险",
      "角色扮演"
    ],
    "release_date": "2026 年 4 月 23 日",
    "review_score": "",
    "store_url": "https://store.steampowered.com/app/2759280"
  },
  {
    "appid": 1165990,
    "name": "Kiln",
    "header_image": "https://shared.akamai.steamstatic.com/store_item_assets/steam/apps/1165990/66d1232d483b485b63545b3ade26a64ed8d0c74d/header.jpg?t=1776956414",
    "short_description": "Double Fine Productions倾情呈献，一场献给玩家的在线陶艺派对格斗盛宴。呼朋唤友，集结各色神灵，转动陶轮，亲手捏塑陶瓷战甲。陶器身躯的尺寸与形状决定了你的战斗风格与技能——齐心协力，浇灭敌人的窑火！",
    "is_free": false,
    "price": "¥ 79.20",
    "original_price": "¥ 88.00",
    "discount_percent": 10,
    "genres": [
      "动作",
      "休闲"
    ],
    "release_date": "2026 年 4 月 23 日",
    "review_score": "",
    "store_url": "https://store.steampowered.com/app/1165990"
  },
  {
    "appid": 1059220,
    "name": "'83",
    "header_image": "https://shared.akamai.steamstatic.com/store_item_assets/steam/apps/1059220/b7ccd7a2b80ef91a8aa93d8cef2755b01aebe8a6/header.jpg?t=1776955754",
    "short_description": "'83 is a 40v40 squad based, objective focused online tactical first person shooter set in a Cold-War-Gone-Hot scenario. It's designed with 'accessible realism' for the most enjoyable, but still hardcore experience that gets you to the action fast, without losing the lethality of war.",
    "is_free": false,
    "price": "¥ 98.10",
    "original_price": "¥ 109.00",
    "discount_percent": 10,
    "genres": [
      "动作",
      "大型多人在线",
      "模拟",
      "策略",
      "抢先体验"
    ],
    "release_date": "2026 年 4 月 23 日",
    "review_score": "",
    "store_url": "https://store.steampowered.com/app/1059220"
  },
  {
    "appid": 2162800,
    "name": "异形工厂2",
    "header_image": "https://shared.akamai.steamstatic.com/store_item_assets/steam/apps/2162800/1431737cec8d83a6d5a0bd9292e2602e85de7e48/header_alt_assets_7_schinese.jpg?t=1776956035",
    "short_description": "深入体验字如其名的“超·大”工厂建造世界！建设规模庞大的多层工厂，用稳健高效的自动化产线尽情兑现您的规划才智！各种升级自动化挑战层出不穷，不过您大可以顺着步子悠着来——反正没有敌人出来捣乱。",
    "is_free": false,
    "price": "¥ 60.00",
    "original_price": "¥ 75.00",
    "discount_percent": 20,
    "genres": [
      "休闲",
      "独立",
      "模拟",
      "策略"
    ],
    "release_date": "2026 年 4 月 23 日",
    "review_score": "",
    "store_url": "https://store.steampowered.com/app/2162800"
  }
]